quick_xinput/__init__.py
quick_xinput/__main__.py
quick_xinput/console.py
quick_xinput/xfuncs.py
quick_xinput-0.1.3.dist-info/LICENSE.md
quick_xinput-0.1.3.dist-info/METADATA
quick_xinput-0.1.3.dist-info/WHEEL
quick_xinput-0.1.3.dist-info/top_level.txt
quick_xinput-0.1.3.dist-info/RECORD
