Metadata-Version: 2.1
Name: quick-xinput
Version: 0.1.3
Summary: Quick selector to enable/disable/toggle xinput devices
Home-page: https://github.com/gikeymarcia/quick-xinput
Author: Mikey Garcia
Author-email: gikeymarcia@gmail.com
License: GPL-3.0
Platform: UNKNOWN
Requires-Dist: pydymenu (>=0.3.1)
Requires-Dist: rich
